lhclient/__init__.py
lhclient/lhclient.py
lhclient-0.1.14.dist-info/entry_points.txt
lhclient-0.1.14.dist-info/WHEEL
lhclient-0.1.14.dist-info/METADATA
lhclient-0.1.14.dist-info/RECORD
