Metadata-Version: 2.1
Name: lhclient
Version: 0.1.14
Summary: The official client for the Logichub API
Home-page: https://logichub.com
License: MIT
Keywords: security,automation,logichub
Author: William Le Ferrand
Author-email: william@logichub.com
Requires-Python: >=2.7, !=3.0.*, !=3.1.*, !=3.2.*, !=3.3.*
Classifier: License :: OSI Approved :: MIT License
Classifier: Programming Language :: Python :: 2
Classifier: Programming Language :: Python :: 2.7
Classifier: Programming Language :: Python :: 3
Classifier: Programming Language :: Python :: 3.4
Classifier: Programming Language :: Python :: 3.5
Classifier: Programming Language :: Python :: 3.6
Classifier: Programming Language :: Python :: 3.7
Requires-Dist: click (>=7.0,<7.1)
Requires-Dist: requests[security] (>=2.18.4,<2.19.0)
